{
  "turn": 0,
  "sim_id": "e1ea2a88-016d-4e0e-9048-1b9fc54b7ac7",
  "timestamp": "2025-04-28T16:55:44.921608",
  "overlays": {
    "hope": 0.5,
    "despair": 0.5,
    "rage": 0.5,
    "fatigue": 0.5,
    "trust": 0.5
  },
  "capital": {
    "nvda": 0.0,
    "msft": 0.0,
    "ibit": 0.0,
    "spy": 0.0,
    "cash": 100000.0
  },
  "variables": {
    "us_10y_yield": 0.0168,
    "cpi_yoy": 276.528,
    "gdp_growth_annual": 7.4,
    "unemployment_rate_fred": 0.045,
    "ppi_final_demand": 240.465,
    "retail_sales_total": 545361.0,
    "industrial_production_index": 100.3542,
    "housing_starts_total": 1587.0,
    "consumer_sentiment_umich": 71.7,
    "trade_balance_goods_services": -66942.0,
    "federal_debt_total": 29617215.0,
    "corporate_profits_after_tax": 2886.711,
    "us_eff_fed_funds_rate": 0.0008,
    "us_prime_loan_rate": 0.0325,
    "us_treasury_yield_1y": 0.0012,
    "us_treasury_yield_5y": 0.0123,
    "us_treasury_yield_30y": 0.0213,
    "monetary_base_total": 6330.9,
    "velocity_m2_money_stock": 1.163,
    "exchange_rate_usd_eur": 1.1643,
    "wti_crude_oil_price": 81.48,
    "brent_crude_oil_price": 84.58,
    "gold_price_london_fix": 0.0,
    "silver_price_london_fix": 0.0,
    "copper_price": 9829.21904761905,
    "baltic_dry_index": 0.0,
    "vix_close_fred": 15.01,
    "consumer_credit_outstanding": 4499221.64,
    "commercial_industrial_loans": 2421.5036,
    "housing_price_index_case_shiller": 273.61400000000003,
    "new_single_family_houses_sold": 416800.0,
    "personal_consumption_expenditures": 16694.0,
    "durable_goods_orders": 257877.0,
    "nonfarm_business_labor_productivity": 0.9,
    "average_hourly_earnings": 31.15,
    "employment_population_ratio": 0.59,
    "participation_rate": 0.618,
    "initial_unemployment_claims": 290000.0,
    "continuing_unemployment_claims": 2268000.0,
    "industrial_capacity_utilization": 78.9984,
    "manufacturing_capacity_utilization": 78.2709,
    "new_orders_manufacturing": 0.0,
    "ism_manufacturing_pmi": 0.0,
    "ism_services_pmi": 0.0,
    "leading_economic_index": 0.0,
    "consumer_price_index_urban": 276.589,
    "personal_consumption_expenditures_price_index": 110.741,
    "gross_private_domestic_investment": 4599.184,
    "net_exports_goods_services": -920.596,
    "government_consumption_investment": 4282.318,
    "corporate_bond_yield_baa": 0.011000000000000001,
    "municipal_bond_yield_aaby": 0.0,
    "commercial_paper_rate_3m": 0.0,
    "treasury_bill_rate_3m": 0.0006,
    "effective_federal_funds_rate_upper_bound": 0.0025,
    "effective_federal_funds_rate_lower_bound": 0.0,
    "reserve_balances_with_federal_reserve_banks": 2799.719,
    "total_assets_of_federal_reserve": 8564943.0,
    "consumer_price_index_medical_care": 0.0,
    "consumer_price_index_energy": 254.669,
    "consumer_price_index_food": 122.522,
    "real_disposable_personal_income": 16648.1,
    "personal_saving_rate": 0.066,
    "net_worth_of_households": 150529.108,
    "total_nonfarm_payroll": 148569.0,
    "average_weekly_hours_manufacturing": 0.0,
    "new_orders_nondefense_capital_goods": 69980.0,
    "shipments_manufacturing": 0.0,
    "inventories_manufacturing": 0.0,
    "housing_completions_total": 0.0,
    "housing_permits_total": 1719.0,
    "existing_home_sales": 0.0,
    "new_single_family_house_price_index": 0.0,
    "case_shiller_20_city_hpi": 0.0,
    "consumer_confidence_board": 0.0,
    "business_confidence_index": 0.0,
    "industrial_production_manufacturing": 0.0,
    "new_orders_consumer_goods": 0.0,
    "shipments_consumer_goods": 0.0,
    "inventories_consumer_goods": 0.0,
    "retail_sales_ex_auto": 0.0,
    "retail_sales_building_material": 0.0,
    "retail_sales_clothing": 0.0,
    "retail_sales_electronics": 0.0,
    "retail_sales_food_beverage": 0.0,
    "retail_sales_health_personal_care": 0.0,
    "retail_sales_sporting_hobby_book": 0.0,
    "retail_sales_general_merchandise": 0.0,
    "retail_sales_motor_vehicle_parts": 0.0,
    "retail_sales_nonstore": 0.0,
    "retail_sales_food_services_drinking": 0.0,
    "new_light_vehicle_sales": 0.0,
    "light_vehicle_sales_domestic": 0.0,
    "light_vehicle_sales_import": 0.0,
    "private_residential_fixed_investment": 0.0,
    "private_nonresidential_fixed_investment": 0.0,
    "exports_goods_services": 0.0,
    "imports_goods_services": 0.0,
    "current_account_balance": 0.0,
    "federal_government_receipts": 0.0,
    "federal_government_outlays": 0.0,
    "federal_surplus_deficit": 0.0,
    "state_local_government_receipts": 0.0,
    "state_local_government_outlays": 0.0,
    "gross_government_investment": 0.0,
    "total_government_consumption_investment": 0.0,
    "nondefense_government_consumption_investment": 0.0,
    "defense_government_consumption_investment": 0.0,
    "federal_government_consumption_investment": 0.0,
    "state_local_government_consumption_investment": 0.0,
    "gross_domestic_product": 0.0,
    "gross_national_product": 0.0,
    "net_domestic_product": 0.0,
    "national_income": 0.0,
    "personal_income": 0.0,
    "disposable_personal_income": 0.0,
    "personal_consumption_expenditures_goods": 0.0,
    "personal_consumption_expenditures_services": 0.0,
    "personal_consumption_expenditures_nondurable_goods": 0.0,
    "change_in_private_inventories": 0.0,
    "exports_goods": 0.0,
    "exports_services": 0.0,
    "imports_goods": 0.0,
    "imports_services": 0.0,
    "balance_of_payments_financial_account": 0.0,
    "net_lending_net_borrowing": 0.0,
    "foreign_direct_investment_in_us": 0.0,
    "us_direct_investment_abroad": 0.0,
    "portfolio_investment_us_assets": 0.0,
    "portfolio_investment_us_liabilities": 0.0,
    "other_investment_us_assets": 0.0,
    "other_investment_us_liabilities": 0.0,
    "reserve_assets": 0.0,
    "net_errors_omissions": 0.0,
    "federal_government_debt_held_by_public": 0.0,
    "federal_government_debt_held_by_intragov": 0.0,
    "state_local_government_debt": 0.0,
    "total_government_debt": 0.0,
    "money_supply_m1": 0.0,
    "money_supply_m2": 0.0,
    "commercial_bank_assets": 0.0,
    "commercial_bank_loans_leases": 0.0,
    "commercial_bank_deposits": 0.0,
    "consumer_price_index_core": 0.0,
    "producer_price_index_final_demand_goods": 0.0,
    "producer_price_index_final_demand_services": 0.0,
    "employment_level_total_nonfarm": 0.0,
    "unemployment_level": 0.0,
    "labor_force_total": 0.0,
    "average_weekly_hours_total_private": 0.0,
    "job_openings_total_nonfarm": 0.0,
    "hires_total_nonfarm": 0.0,
    "separations_total_nonfarm": 0.0,
    "quits_total_nonfarm": 0.0,
    "layoffs_discharges_total_nonfarm": 0.0,
    "manufacturing_new_orders_all_industries": 0.0,
    "manufacturing_shipments_all_industries": 0.0,
    "manufacturing_inventories_all_industries": 0.0,
    "manufacturing_unfilled_orders_all_industries": 0.0,
    "retail_sales_motor_vehicle_parts_dealers": 0.0,
    "retail_sales_furniture_home_furnishings": 0.0,
    "retail_sales_electronics_appliance": 0.0,
    "retail_sales_building_material_garden": 0.0,
    "retail_sales_food_beverage_stores": 0.0,
    "retail_sales_health_personal_care_stores": 0.0,
    "retail_sales_gasoline_stations": 0.0,
    "retail_sales_clothing_accessories_stores": 0.0,
    "retail_sales_sporting_goods_hobby_book": 0.0,
    "retail_sales_general_merchandise_stores": 0.0,
    "retail_sales_miscellaneous_store_retailers": 0.0,
    "retail_sales_nonstore_retailers": 0.0,
    "food_services_drinking_places_sales": 0.0,
    "housing_inventory_for_sale": 0.0,
    "housing_vacancy_rate_rental": 0.0,
    "housing_vacancy_rate_homeowner": 0.0,
    "median_asking_rent_us": 0.0,
    "median_asking_sales_price_us": 0.0,
    "personal_consumption_expenditures_chain_price_index": 0.0,
    "personal_consumption_expenditures_ex_food_energy_chain_price_index": 0.0,
    "gross_domestic_product_chain_price_index": 0.0,
    "producer_price_index_finished_goods": 0.0,
    "producer_price_index_intermediate_goods": 0.0,
    "producer_price_index_crude_goods": 0.0,
    "employment_cost_index_total_compensation": 0.0,
    "employment_cost_index_wages_salaries": 0.0,
    "employment_cost_index_benefits": 0.0,
    "unit_labor_costs_nonfarm_business": 0.0,
    "nonfarm_business_sector_output_per_hour": 0.0,
    "nonfarm_business_sector_compensation_per_hour": 0.0,
    "manufacturing_sector_output_per_hour": 0.0,
    "manufacturing_sector_compensation_per_hour": 0.0,
    "manufacturing_sector_unit_labor_costs": 0.0,
    "business_sector_output_per_hour": 0.0,
    "business_sector_compensation_per_hour": 0.0,
    "business_sector_unit_labor_costs": 0.0,
    "nonfinancial_corporate_business_sector_output_per_hour": 0.0,
    "nonfinancial_corporate_business_sector_compensation_per_hour": 0.0,
    "nonfinancial_corporate_business_sector_unit_labor_costs": 0.0,
    "real_gdp_per_capita": 0.0,
    "gross_national_income": 0.0,
    "net_national_product": 0.0,
    "national_income_private_industries": 0.0,
    "national_income_government": 0.0,
    "personal_income_ex_transfer_payments": 0.0,
    "disposable_personal_income_per_capita": 0.0,
    "personal_consumption_expenditures_per_capita": 0.0,
    "gross_private_domestic_investment_residential_structures": 0.0,
    "gross_private_domestic_investment_residential_equipment": 0.0,
    "gross_private_domestic_investment_nonresidential_structures": 0.0,
    "gross_private_domestic_investment_nonresidential_equipment": 0.0,
    "change_in_private_inventories_farm": 0.0,
    "change_in_private_inventories_nonfarm": 0.0,
    "exports_goods_industrial_supplies": 0.0,
    "exports_goods_capital_goods": 0.0,
    "exports_goods_automotive": 0.0,
    "exports_goods_consumer_goods": 0.0,
    "exports_goods_foods_feeds_beverages": 0.0,
    "imports_goods_industrial_supplies": 0.0,
    "imports_goods_capital_goods": 0.0,
    "imports_goods_automotive": 0.0,
    "imports_goods_consumer_goods": 0.0,
    "imports_goods_foods_feeds_beverages": 0.0,
    "balance_of_payments_goods": 0.0,
    "balance_of_payments_services": 0.0,
    "balance_of_payments_primary_income": 0.0,
    "balance_of_payments_secondary_income": 0.0,
    "federal_government_current_receipts": 0.0,
    "federal_government_current_expenditures": 0.0,
    "state_local_government_current_receipts": 0.0,
    "state_local_government_current_expenditures": 0.0,
    "total_government_current_receipts": 0.0,
    "total_government_current_expenditures": 0.0,
    "total_government_net_saving": 0.0,
    "net_operating_surplus_government": 0.0,
    "consumption_of_fixed_capital_government": 0.0,
    "net_domestic_product_government": 0.0,
    "national_income_government_enterprises": 0.0,
    "national_income_general_government": 0.0,
    "personal_income_wages_salaries": 0.0,
    "personal_income_supplements_to_wages": 0.0,
    "personal_income_proprietors_income": 0.0,
    "personal_income_rental_income": 0.0,
    "personal_income_personal_dividend_income": 0.0,
    "personal_income_personal_interest_income": 0.0,
    "personal_income_personal_current_transfer_receipts": 0.0,
    "personal_income_less_contributions_social_insurance": 0.0,
    "disposable_personal_income_personal_current_taxes": 0.0,
    "personal_outlays": 0.0,
    "personal_consumption_expenditures_durable_goods_motor_vehicles_parts": 0.0,
    "personal_consumption_expenditures_durable_goods_furnishings_durable_household_equipment": 0.0,
    "personal_consumption_expenditures_durable_goods_recreational_goods_vehicles": 0.0,
    "personal_consumption_expenditures_durable_goods_other": 0.0,
    "personal_consumption_expenditures_nondurable_goods_food_beverages": 0.0,
    "personal_consumption_expenditures_nondurable_goods_clothing_footwear": 0.0,
    "personal_consumption_expenditures_nondurable_goods_gasoline_other_energy_goods": 0.0,
    "personal_consumption_expenditures_nondurable_goods_other": 0.0,
    "personal_consumption_expenditures_services_housing_utilities": 0.0,
    "personal_consumption_expenditures_services_health_care": 0.0,
    "personal_consumption_expenditures_services_transportation": 0.0,
    "personal_consumption_expenditures_services_recreation": 0.0,
    "personal_consumption_expenditures_services_food_services_accommodations": 0.0,
    "personal_consumption_expenditures_services_financial_insurance": 0.0,
    "personal_consumption_expenditures_services_other": 0.0,
    "spx_close": 4549.77978515625,
    "vix_close": 15.010000228881836,
    "djia_close": 35603.078125,
    "nasdaq_composite_close": 15215.7001953125,
    "russell_2000_close": 2296.179931640625,
    "ftse_100_close": 7190.2998046875,
    "dax_performance_close": 15472.5595703125,
    "nikkei_225_close": 28708.580078125,
    "hang_seng_index_close": 26017.529296875,
    "shanghai_composite_close": 3594.780029296875,
    "sp_tsx_composite_close": 21212.400390625,
    "all_ordinaries_close": 7728.5,
    "ipc_mexico_close": 52020.05078125,
    "ibovespa_brazil_close": 107735.0,
    "cac_40_close": 6686.169921875,
    "euro_stoxx_50_close": 4155.72998046875,
    "swiss_market_index_close": 12039.1396484375,
    "s_p_asx_200_close": 7415.39990234375,
    "korea_composite_stock_price_index_close": 3007.330078125,
    "nifty_50_close": 18178.099609375,
    "sensex_india_close": 60923.5,
    "bse_100_india_close": NaN,
    "crypto_bitcoin_usd": 62210.171875,
    "crypto_ethereum_usd": 4054.32275390625,
    "crypto_ripple_usd": 1.0893150568008423,
    "crypto_litecoin_usd": 196.8691864013672,
    "crypto_cardano_usd": 2.1365909576416016,
    "crypto_polkadot_usd": 42.846519470214844,
    "crypto_solana_usd": 190.3184356689453,
    "crypto_dogecoin_usd": 0.24239100515842438,
    "crypto_shiba_inu_usd": 2.700000004551839e-05,
    "crypto_wrapped_bitcoin_usd": 62291.109375,
    "gold_futures": 1781.199951171875,
    "silver_futures": 24.149999618530273,
    "copper_futures": 4.58650016784668,
    "crude_oil_futures_wti": 82.5,
    "brent_oil_futures": 84.61000061035156,
    "natural_gas_futures": 5.114999771118164,
    "corn_futures": 532.25,
    "wheat_futures": 741.25,
    "soybean_futures": 1224.0,
    "sugar_futures": 18.940000534057617,
    "coffee_futures": 203.3000030517578,
    "cocoa_futures": 2555.0,
    "cotton_futures": 106.13999938964844,
    "us_dollar_index_futures": 93.75800323486328,
    "euro_usd_futures": 1.1655012369155884,
    "usd_jpy_futures": 114.38899993896484,
    "gbp_usd_futures": 1.3822999000549316,
    "aud_usd_futures": 0.7515299320220947,
    "usd_cad_futures": 1.2324399948120117,
    "usd_chf_futures": 0.9187999963760376,
    "nzd_usd_futures": 0.71986985206604,
    "usd_inr_futures": 74.80919647216797,
    "cny_usd_futures": 6.392899990081787,
    "us_10y_treasury_bond_futures": 130.1875,
    "us_30y_treasury_bond_futures": 157.75,
    "vix_futures": NaN,
    "sp_500_futures": 4541.75,
    "nasdaq_100_futures": 15478.75,
    "dow_jones_futures": 35480.0,
    "russell_2000_futures": 2294.10009765625,
    "apple_stock": 146.69529724121094,
    "microsoft_stock": 301.7460021972656,
    "google_stock_a": 141.21087646484375,
    "amazon_stock": 171.75050354003906,
    "tesla_stock": 298.0,
    "facebook_stock": 340.2762756347656,
    "nvidia_stock": 22.649465560913086,
    "berkshire_hathaway_b_stock": 286.82000732421875,
    "jp_morgan_chase_stock": 154.0865020751953,
    "johnson_johnson_stock": 147.62913513183594,
    "visa_stock": 224.2186737060547,
    "mastercard_stock": 348.8946838378906,
    "unitedhealth_group_stock": 420.40496826171875,
    "exxon_mobil_stock": 55.14295959472656,
    "chevron_stock": 97.27547454833984,
    "pfizer_stock": 36.49361801147461,
    "merck_stock": 73.13715362548828,
    "walmart_stock": 46.57746505737305,
    "home_depot_stock": 334.2569274902344,
    "mcdonalds_stock": 222.8922119140625,
    "cocacola_stock": 48.91405487060547,
    "pepsico_stock": 143.7781219482422,
    "tech_sector_etf": 154.43357849121094,
    "health_sector_etf": 124.06866455078125,
    "energy_sector_etf": 50.35673904418945,
    "financial_sector_etf": 37.59391784667969,
    "consumer_discretionary_sector_etf": 187.7570343017578,
    "consumer_staples_sector_etf": 64.54566955566406,
    "industrials_sector_etf": 98.69776916503906,
    "materials_sector_etf": 79.12045288085938,
    "real_estate_sector_etf": 42.04835510253906,
    "utilities_sector_etf": 60.0305061340332,
    "communication_services_sector_etf": 79.31098937988281,
    "vanguard_total_stock_market_etf": 222.8360137939453,
    "vanguard_sp_500_etf": 395.5787658691406,
    "ishares_core_us_aggregate_bond_etf": 102.77113342285156,
    "vanguard_total_bond_market_etf": 76.06797790527344,
    "ishares_jpmorgan_usd_emerging_markets_bond_etf": 91.57046508789062,
    "ishares_iboxx_usd_investment_grade_corporate_bond_etf": 115.33561706542969,
    "ishares_iboxx_usd_high_yield_corporate_bond_etf": 71.66275787353516,
    "spdr_gold_shares": 166.75,
    "ishares_silver_trust": 22.350000381469727,
    "united_states_oil_fund": 57.40999984741211,
    "united_states_gasoline_fund": 43.54999923706055,
    "united_states_natural_gas_fund": 72.63999938964844,
    "invesco_db_agriculture_fund": 17.361841201782227,
    "invesco_db_energy_fund": 16.577661514282227,
    "invesco_db_gold_fund": 51.18989944458008,
    "invesco_db_silver_fund": 33.58000183105469,
    "invesco_db_us_dollar_index_bullish": 22.440155029296875,
    "invesco_db_us_dollar_index_bearish": 18.560504913330078,
    "public_trust_level": 0.0,
    "crypto_instability": 0.0,
    "ai_policy_risk": 0.0,
    "geopolitical_stability": 0.0,
    "media_sentiment_score": 0.0,
    "social_media_sentiment": 0.0,
    "news_sentiment_score": 0.0,
    "policy_sentiment_score": 0.0,
    "eu_inflation_index": 0.0,
    "asia_inflation_index": 0.0,
    "eu_unemployment_rate": 0.0,
    "asia_unemployment_rate": 0.0,
    "us_public_trust_level": 0.0,
    "eu_public_trust_level": 0.0,
    "asia_public_trust_level": 0.0
  },
  "event_count": 0,
  "metadata": {}
}